zhangTCD/RamanMap.py
zhangTCD/__init__.py
zhangTCD/figProc.py
zhangTCD/global_fun.py
zhangTCD/hyperImg.py
zhangTCD/spc.py
zhangTCD/spcMap.py
zhangTCD/sub.py
zhangTCD-0.1.4.dist-info/LICENSE
zhangTCD-0.1.4.dist-info/METADATA
zhangTCD-0.1.4.dist-info/WHEEL
zhangTCD-0.1.4.dist-info/top_level.txt
zhangTCD-0.1.4.dist-info/RECORD
