Metadata-Version: 2.1
Name: zhangTCD
Version: 0.1.4
Summary: For lab data management
Home-page: https://github.com/hozhangTCD/zhangTCD
Author: Hongzhou Zhang
Author-email: hozhang@tcd.ie
Classifier: Programming Language :: Python :: 3
Classifier: License :: OSI Approved :: MIT License
Classifier: Operating System :: OS Independent
Requires-Python: >=3.7
License-File: LICENSE
